LICENSE
MANIFEST.in
README.md
setup.cfg
setup.py
tests/integration/__init__.py
tests/integration/test_integration.py
tests/unittest/__init__.py
tests/unittest/test_consensus.py
tests/unittest/test_crypto.py
tests/unittest/test_documents.py
tests/unittest/test_parsers.py
torpy/__init__.py
torpy/__main__.py
torpy/cache_storage.py
torpy/cell_socket.py
torpy/cells.py
torpy/circuit.py
torpy/client.py
torpy/consesus.py
torpy/crypto.py
torpy/crypto_common.py
torpy/crypto_state.py
torpy/dirs.py
torpy/guard.py
torpy/hiddenservice.py
torpy/keyagreement.py
torpy/parsers.py
torpy/stream.py
torpy/utils.py
torpy.egg-info/PKG-INFO
torpy.egg-info/SOURCES.txt
torpy.egg-info/dependency_links.txt
torpy.egg-info/entry_points.txt
torpy.egg-info/requires.txt
torpy.egg-info/top_level.txt
torpy/cli/__init__.py
torpy/cli/console.py
torpy/cli/socks.py
torpy/documents/__init__.py
torpy/documents/basics.py
torpy/documents/dir_key_certificate.py
torpy/documents/factory.py
torpy/documents/items.py
torpy/documents/network_status.py
torpy/documents/network_status_diff.py
torpy/http/__init__.py
torpy/http/adapter.py
torpy/http/base.py
torpy/http/client.py
torpy/http/requests.py
torpy/http/urlopener.py