Metadata-Version: 2.1
Name: torpy
Version: 1.1.5
Summary: Pure python tor protocol implementation
Home-page: https://github.com/torpyorg/torpy
Author: James Brown
License: UNKNOWN
Project-URL: Bug Reports, https://github.com/torpyorg/torpy/issues
Project-URL: Source, https://github.com/torpyorg/torpy/
Keywords: python proxy anonymity privacy socks tor protocol onion hiddenservice
Platform: UNKNOWN
Classifier: Development Status :: 4 - Beta
Classifier: Intended Audience :: Developers
Classifier: License :: OSI Approved :: Apache Software License
Classifier: Programming Language :: Python :: 3.6
Classifier: Programming Language :: Python :: 3.7
Classifier: Programming Language :: Python :: 3.8
Classifier: Programming Language :: Python :: 3.9
Requires-Python: >=3.6
Provides-Extra: requests
